jquote_api/__init__.py
jquote_api/common.py
jquote_api/getAStockCodeApi.py
jquote_api/getHKFinanceData.py
jquote_api-1.0.6.8.dist-info/METADATA
jquote_api-1.0.6.8.dist-info/WHEEL
jquote_api-1.0.6.8.dist-info/top_level.txt
jquote_api-1.0.6.8.dist-info/RECORD
